nautobot_app_livedata/__init__.py
nautobot_app_livedata/api/__init__.py
nautobot_app_livedata/api/serializers.py
nautobot_app_livedata/api/urls.py
nautobot_app_livedata/api/views.py
nautobot_app_livedata/app-config-schema.json
nautobot_app_livedata/jobs.py
nautobot_app_livedata/nornir_plays/__init__.py
nautobot_app_livedata/nornir_plays/processor.py
nautobot_app_livedata/signals.py
nautobot_app_livedata/static/nautobot_app_livedata/docs/404.html
nautobot_app_livedata/static/nautobot_app_livedata/docs/admin/compatibility_matrix.html
nautobot_app_livedata/static/nautobot_app_livedata/docs/admin/install.html
nautobot_app_livedata/static/nautobot_app_livedata/docs/admin/release_notes/index.html
nautobot_app_livedata/static/nautobot_app_livedata/docs/admin/release_notes/version_2.4.html
nautobot_app_livedata/static/nautobot_app_livedata/docs/admin/uninstall.html
nautobot_app_livedata/static/nautobot_app_livedata/docs/admin/upgrade.html
nautobot_app_livedata/static/nautobot_app_livedata/docs/assets/_mkdocstrings.css
nautobot_app_livedata/static/nautobot_app_livedata/docs/assets/extra.css
nautobot_app_livedata/static/nautobot_app_livedata/docs/assets/favicon.ico
nautobot_app_livedata/static/nautobot_app_livedata/docs/assets/icon-livedata.png
nautobot_app_livedata/static/nautobot_app_livedata/docs/assets/images/favicon.png
nautobot_app_livedata/static/nautobot_app_livedata/docs/assets/javascripts/bundle.f55a23d4.min.js
nautobot_app_livedata/static/nautobot_app_livedata/docs/assets/javascripts/bundle.f55a23d4.min.js.map
nautobot_app_livedata/static/nautobot_app_livedata/docs/assets/javascripts/lunr/min/lunr.ar.min.js
nautobot_app_livedata/static/nautobot_app_livedata/docs/assets/javascripts/lunr/min/lunr.da.min.js
nautobot_app_livedata/static/nautobot_app_livedata/docs/assets/javascripts/lunr/min/lunr.de.min.js
nautobot_app_livedata/static/nautobot_app_livedata/docs/assets/javascripts/lunr/min/lunr.du.min.js
nautobot_app_livedata-2.4.9.dist-info/LICENSE
nautobot_app_livedata-2.4.9.dist-info/METADATA
nautobot_app_livedata-2.4.9.dist-info/WHEEL
nautobot_app_livedata-2.4.9.dist-info/RECORD
