Metadata-Version: 2.1
Name: nautobot_app_livedata
Version: 2.4.9
Summary: Provides a live view of network data within Nautobot.
Home-page: https://github.com/jifox/nautobot-app-livedata.git
License: Apache-2.0
Keywords: nautobot,nautobot-app,nautobot-plugin
Author: Josef Fuchs
Author-email: josef.fuchs@j-fuchs.at
Requires-Python: >=3.9.2,<3.13
Classifier: Development Status :: 5 - Production/Stable
Classifier: Intended Audience :: Developers
Classifier: License :: OSI Approved :: Apache Software License
Classifier: Programming Language :: Python :: 3
Classifier: Programming Language :: Python :: 3.10
Classifier: Programming Language :: Python :: 3.11
Classifier: Programming Language :: Python :: 3.12
Classifier: Programming Language :: Python :: 3.9
Provides-Extra: all
Requires-Dist: h11 (>=0.16.0,<0.17.0)
Requires-Dist: jsonschema (>=4.7.0,<5.0.0)
Requires-Dist: nautobot (>=2.4.15,<2.5.0)
Requires-Dist: nautobot-plugin-nornir (>=2.2.0,<2.3.0)
Requires-Dist: to-json-schema
Project-URL: Documentation, https://nautobot-app-livedata.readthedocs.io/en/latest/
Project-URL: Repository, https://github.com/jifox/nautobot-app-livedata.git
